Metadata-Version: 2.1
Name: dbgclient
Version: 1.1.0
Summary: a simple script to create bot using HTTP API
Home-page: https://gitlab.com/dbgid/dbgclient
Author: DBG ID
Author-email: me@dbgidofficial.my.id
License: MIT
Project-URL: issues, https://gitlab.com/dbgid/dbgclient/issues
Classifier: Programming Language :: Python :: 3
Classifier: License :: OSI Approved :: MIT License
Classifier: Operating System :: OS Independent
Requires-Python: >=3.9
License-File: LICENSE
